Workbook
Name aporte: Planilha1!$D$17
Name qtd_anos: Planilha1!$D$18
Name rendimento_carteira: Planilha1!$D$13
Name taxa_rendimento: Planilha1!$D$19

Sheet Planilha1
B11: CONFIGURAÇÕES
B12: Salário | D12: 2987
B13: Remdimento Carteira | D13: 0.0087
B14: Sugestão de investimento | D14: =D12*0.3 -> 896.1
B16: INVESTIMENTO MENSAL
B17: Quanto investir por mês? | D17: 400
B18: Por Quantos Anos? | D18: 5
B19: Taxa de Rendimento mensal? | D19: 0.0108
B20: Patrimônio acumulado? | D20: =FV(D19,D18*12,D17*-1) -> 33521.608
B21: Dividendos Mensais? | D21: =D20*D19 -> 362.03336
B23: CENÁRIOS | D23: Dividendo
A24: 2 | B24: Quantos em 2 anos? | C24: =FV($D$19,$A24*12,$D$17*-1) -> 10892.345 | D24: =C24*rendimento_carteira -> 94.763406
A25: 5 | B25: Quantos em 5 anos? | C25: =FV($D$19,$A25*12,$D$17*-1) -> 33521.608 | D25: =C25*rendimento_carteira -> 291.63799
A26: 10 | B26: Quantos em 10 anos? | C26: =FV($D$19,$A26*12,$D$17*-1) -> 97383.067 | D26: =C26*rendimento_carteira -> 847.23268
A27: 20 | B27: Quantos em 20 anos? | C27: =FV($D$19,$A27*12,$D$17*-1) -> 450819.6 | D27: =C27*rendimento_carteira -> 3922.1305
A28: 30 | B28: Quantos em 30 anos? | C28: =FV($D$19,$A28*12,$D$17*-1) -> 1733561.9 | D28: =C28*rendimento_carteira -> 15081.989
B31: Perfil | C31: Conservador
B32: Valor Investido por mês | C32: 500
B34: Tipo de FII | C34: Percentual Sugerido | D34: Valores
B35: Papel | C35: =VLOOKUP(($C$31&"-"&B35),Planilha2!$A$1:$D$20,4,FALSE) -> 0.3 | D35: =C35*$C$32 -> 150
B36: Tijolo | C36: =VLOOKUP(($C$31&"-"&B36),Planilha2!$A$1:$D$20,4,FALSE) -> 0.5 | D36: =C36*$C$32 -> 250
B37: Hibridos | C37: =VLOOKUP(($C$31&"-"&B37),Planilha2!$A$1:$D$20,4,FALSE) -> 0.1 | D37: =C37*$C$32 -> 50
B38: FOF's | C38: =VLOOKUP(($C$31&"-"&B38),Planilha2!$A$1:$D$20,4,FALSE) -> 0.1 | D38: =C38*$C$32 -> 50
B39: Desenvolvimento | C39: =VLOOKUP(($C$31&"-"&B39),Planilha2!$A$1:$D$20,4,FALSE) -> 0 | D39: =C39*$C$32 -> 0
B40: Hotelarias | C40: =VLOOKUP(($C$31&"-"&B40),Planilha2!$A$1:$D$20,4,FALSE) -> 0 | D40: =C40*$C$32 -> 0

Sheet Planilha2
A2: Chave | B2: Perfil | C2: Tipo de FII | D2: %
A3: =B3&"-"&C3 -> Conservador-Papel | B3: Conservador | C3: Papel | D3: 0.3 | I3: %
A4: =B4&"-"&C4 -> Conservador-Tijolo | B4: Conservador | C4: Tijolo | D4: 0.5 | H4: =A10 -> Moderado-Tijolo | I4: =VLOOKUP(H4,$A$2:$D$20,4,FALSE) -> 0.4
A5: =B5&"-"&C5 -> Conservador-Hibridos | B5: Conservador | C5: Hibridos | D5: 0.1
A6: =B6&"-"&C6 -> Conservador-FOF's | B6: Conservador | C6: FOF's | D6: 0.1
A7: =B7&"-"&C7 -> Conservador-Desenvolvimento | B7: Conservador | C7: Desenvolvimento | D7: 0
A8: =B8&"-"&C8 -> Conservador-Hotelarias | B8: Conservador | C8: Hotelarias | D8: 0
A9: =B9&"-"&C9 -> Moderado-Papel | B9: Moderado | C9: Papel | D9: 0.32
A10: =B10&"-"&C10 -> Moderado-Tijolo | B10: Moderado | C10: Tijolo | D10: 0.4
A11: =B11&"-"&C11 -> Moderado-Hibridos | B11: Moderado | C11: Hibridos | D11: 0.08
A12: =B12&"-"&C12 -> Moderado-FOF's | B12: Moderado | C12: FOF's | D12: 0.1
A13: =B13&"-"&C13 -> Moderado-Desenvolvimento | B13: Moderado | C13: Desenvolvimento | D13: 0.1
A14: =B14&"-"&C14 -> Moderado-Hotelarias | B14: Moderado | C14: Hotelarias | D14: 0.1
A15: =B15&"-"&C15 -> Agressivo-Papel | B15: Agressivo | C15: Papel | D15: 0.5
A16: =B16&"-"&C16 -> Agressivo-Tijolo | B16: Agressivo | C16: Tijolo | D16: 0.1
... A20: =B20&"-"&C20 -> Agressivo-Hotelarias | B20: Agressivo | C20: Hotelarias | D20: 0.1
